README.md
setup.cfg
setup.py
distributions/Binomialdistribution.py
distributions/Gaussiandistribution.py
distributions/Generaldistribution.py
distributions/__init__.py
distributions_prob99.egg-info/PKG-INFO
distributions_prob99.egg-info/SOURCES.txt
distributions_prob99.egg-info/dependency_links.txt
distributions_prob99.egg-info/not-zip-safe
distributions_prob99.egg-info/top_level.txt